COPYING
MANIFEST.in
ez_setup.py
pat2pdf
postsetup.py
setup.py
Twisted_Goodies.egg-info/PKG-INFO
Twisted_Goodies.egg-info/SOURCES.txt
Twisted_Goodies.egg-info/dependency_links.txt
Twisted_Goodies.egg-info/requires.txt
Twisted_Goodies.egg-info/top_level.txt
Twisted_Goodies.egg-info/zip-safe
misc/etc_init.d_simpleserver
misc/etc_simpleserver_server.conf
misc/etc_simpleserver_server.tac
misc/var_www_foss.tellectual.com_index.py
twisted_goodies/__init__.py
twisted_goodies/misc/__init__.py
twisted_goodies/misc/test/__init__.py
twisted_goodies/misc/test/test_misc.py
twisted_goodies/qtwisted/__init__.py
twisted_goodies/qtwisted/qt4reactor.py
twisted_goodies/qtwisted/test/__init__.py
twisted_goodies/simpleserver/__init__.py
twisted_goodies/simpleserver/pop3.py
twisted_goodies/simpleserver/service.py
twisted_goodies/simpleserver/http/__init__.py
twisted_goodies/simpleserver/http/auth.py
twisted_goodies/simpleserver/http/manhole.py
twisted_goodies/simpleserver/http/startup.py
twisted_goodies/simpleserver/http/util.py
twisted_goodies/simpleserver/http/wsgi.py
twisted_goodies/simpleserver/http/resources/__init__.py
twisted_goodies/simpleserver/http/resources/basic.py
twisted_goodies/simpleserver/http/resources/external.py
twisted_goodies/simpleserver/http/resources/projects.py
twisted_goodies/simpleserver/http/resources/test/__init__.py
twisted_goodies/simpleserver/http/resources/test/test_projects.py
twisted_goodies/simpleserver/http/rest/__init__.py
twisted_goodies/simpleserver/http/rest/directives.py
twisted_goodies/simpleserver/http/rest/page.py
twisted_goodies/simpleserver/http/test/__init__.py
twisted_goodies/simpleserver/smtp/__init__.py
twisted_goodies/simpleserver/test/__init__.py
twisted_goodies/test/__init__.py
twisted_goodies/test/mock.py
twisted_goodies/webfetch/__init__.py
twisted_goodies/webfetch/fetch.py
twisted_goodies/webfetch/http.py
twisted_goodies/webfetch/patents.py
twisted_goodies/webfetch/test/__init__.py
twisted_goodies/webfetch/test/app.tbz2
twisted_goodies/webfetch/test/eepatents.com_background.html
twisted_goodies/webfetch/test/eepatents.com_index.html
twisted_goodies/webfetch/test/err404.html
twisted_goodies/webfetch/test/patent.tbz2
