Metadata-Version: 1.0
Name: Twisted-Goodies
Version: 0.4
Summary:  Asynchronous HTTP fetching, cluster management, and other goodies for the Twisted framework. 
Home-page: http://foss.eepatents.com/Twisted-Goodies/
Author: Edwin A. Suominen
Author-email: ed@eepatents.com
License: GPL
Keywords: Twisted,asynchronous,web,fetch,patent,wget
Platform: OS Independent
Classifier: Development Status :: 4 - Beta
Classifier: Intended Audience :: Developers
Classifier: Intended Audience :: System Administrators
Classifier: License :: OSI Approved :: GNU General Public License (GPL)
Classifier: Operating System :: OS Independent
Classifier: Programming Language :: Python
Classifier: Topic :: Software Development :: Libraries :: Python Modules
